drebedengi/__init__.py
drebedengi/api.py
drebedengi/model.py
drebedengi/py.typed
drebedengi/utils.py
drebedengi_python_api-0.2.0.dist-info/LICENSE
drebedengi_python_api-0.2.0.dist-info/WHEEL
drebedengi_python_api-0.2.0.dist-info/METADATA
drebedengi_python_api-0.2.0.dist-info/RECORD
