Metadata-Version: 2.1
Name: drebedengi-python-api
Version: 0.2.0
Summary: Python wrapper for Drebedengi SOAP API.
Home-page: https://github.com/mishamsk/drebedengi-python-api
License: GPL-3.0-only
Author: Mike Perlov
Author-email: mishamsk@gmail.com
Requires-Python: >=3.10,<=3.11
Classifier: Development Status :: 2 - Pre-Alpha
Classifier: Intended Audience :: Developers
Classifier: License :: OSI Approved :: GNU General Public License v3 (GPLv3)
Classifier: Natural Language :: English
Classifier: Programming Language :: Python :: 3
Classifier: Programming Language :: Python :: 3.10
Classifier: Programming Language :: Python :: 3.10
Classifier: Programming Language :: Python :: 3.11
Requires-Dist: attrs (>=22.1.0,<23.0.0)
Requires-Dist: click (>=8.1.3,<9.0.0)
Requires-Dist: zeep (>=4.2.0,<5.0.0)
